fb/__init__.py
fb/exceptions.py
fb/leagueids.py
fb/leagueproperties.py
fb_data_cli-0.0.1.dist-info/LICENSE
fb_data_cli-0.0.1.dist-info/METADATA
fb_data_cli-0.0.1.dist-info/WHEEL
fb_data_cli-0.0.1.dist-info/entry_points.txt
fb_data_cli-0.0.1.dist-info/top_level.txt
fb_data_cli-0.0.1.dist-info/RECORD
